gstore_api/GstoreConnector.py
gstore_api/__init__.py
gstore_api/gStoreCloud.py
gstore_api/test.py
gstore_api-1.5.dist-info/LICENSE
gstore_api-1.5.dist-info/METADATA
gstore_api-1.5.dist-info/WHEEL
gstore_api-1.5.dist-info/top_level.txt
gstore_api-1.5.dist-info/RECORD
