Metadata-Version: 2.1
Name: gstore-api
Version: 1.5
Summary: gstore_api是一个用于python链接gStore的工具类
Home-page: https://github.com/pkumod/gStore
Author: liwenjie
Author-email: liwenjiehn@pku.edu.cn
License: UNKNOWN
Platform: UNKNOWN
Requires-Python: >=3.6
